prozt/__init__.py
prozt/prozt.py
prozt-0.0.3.dist-info/METADATA
prozt-0.0.3.dist-info/WHEEL
prozt-0.0.3.dist-info/top_level.txt
prozt-0.0.3.dist-info/RECORD
