Metadata-Version: 2.1
Name: prozt
Version: 0.0.3
Summary: colorful print command
Home-page: https://github.com/Prootzel/prozt
Author: Prootzel
Author-email: lirkel123@gmail.com
Classifier: Programming Language :: Python :: 3
Classifier: License :: OSI Approved :: MIT License
Classifier: Operating System :: OS Independent
